README.rst
setup.py
zerobug/.coveragerc
zerobug/LICENSE
zerobug/__init__.py
zerobug/__main__.py
zerobug/z0testlib.py
zerobug/z0testrc
zerobug.egg-info/PKG-INFO
zerobug.egg-info/SOURCES.txt
zerobug.egg-info/dependency_links.txt
zerobug.egg-info/entry_points.txt
zerobug.egg-info/not-zip-safe
zerobug.egg-info/requires.txt
zerobug.egg-info/top_level.txt
zerobug/_travis/__init__.py
zerobug/_travis/build_cmd
zerobug/_travis/travis_after_tests_success
zerobug/_travis/travis_install_env
zerobug/_travis/travis_run_pypi_tests
zerobug/_travis/cfg/coveragerc
zerobug/_travis/cfg/travis_run_flake8.cfg
zerobug/_travis/cfg/travis_run_flake8_AVERAGE.cfg
zerobug/_travis/cfg/travis_run_flake8_MINIMAL.cfg
zerobug/_travis/cfg/travis_run_flake8_NEARBY.cfg
zerobug/_travis/cfg/travis_run_flake8_REDUCED.cfg
zerobug/_travis/cfg/travis_run_flake8__init__.cfg
zerobug/_travis/cfg/travis_run_flake8__init__AVERAGE.cfg
zerobug/_travis/cfg/travis_run_flake8__init__MINIMAL.cfg
zerobug/_travis/cfg/travis_run_flake8__init__NEARBY.cfg
zerobug/_travis/cfg/travis_run_flake8__init__REDUCED.cfg
zerobug/_travis/cfg/travis_run_pylint.cfg
zerobug/_travis/cfg/travis_run_pylint_61.cfg
zerobug/_travis/cfg/travis_run_pylint_70.cfg
zerobug/_travis/cfg/travis_run_pylint_PYPI.cfg
zerobug/_travis/cfg/travis_run_pylint_PYPI2.cfg
zerobug/_travis/cfg/travis_run_pylint_beta.cfg
zerobug/_travis/cfg/travis_run_pylint_exclude_61.cfg
zerobug/_travis/cfg/travis_run_pylint_exclude_70.cfg
zerobug/_travis/cfg/travis_run_pylint_exclude_AVERAGE.cfg
zerobug/_travis/cfg/travis_run_pylint_exclude_MINIMAL.cfg
zerobug/_travis/cfg/travis_run_pylint_exclude_NEARBY.cfg
zerobug/_travis/cfg/travis_run_pylint_exclude_REDUCED.cfg
zerobug/_travis/cfg/travis_run_pylint_pr.cfg
zerobug/_travis/cfg/travis_run_shellcheck.cfg
zerobug/_travis/cfg/travis_run_shellcheck_MINIMAL.cfg
zerobug/_travis/cfg/travis_run_shellcheck_REDUCED.cfg
zerobug/docs/.readthedocs.yaml
zerobug/docs/MAINPAGE.rst
zerobug/docs/Makefile
zerobug/docs/conf.py
zerobug/docs/index.rst
zerobug/docs/logozero_180x46.png
zerobug/docs/requirements.txt
zerobug/docs/rtd_automodule.rst
zerobug/docs/rtd_changelog.rst
zerobug/docs/rtd_credits.rst
zerobug/docs/rtd_description.rst
zerobug/egg-info/CHANGELOG.rst
zerobug/egg-info/DESCRIPTION.rst
zerobug/egg-info/FEATURES.rst
zerobug/egg-info/USAGE.rst
zerobug/egg-info/__manifest__.rst
zerobug/egg-info/usage_code_example.rst
zerobug/egg-info/usage_code_reference.rst
